Metadata-Version: 2.1
Name: pyqt-hyperchat-server
Version: 0.1.81
Summary: pyqt_hyperchat_server
Home-page: UNKNOWN
Author: Wrexan
Author-email: fwrexan@gmail.com
License: UNKNOWN
Platform: UNKNOWN
Requires-Dist: PyQt5
Requires-Dist: sqlalchemy
Requires-Dist: pycryptodome
Requires-Dist: pycryptodomex
